bazooka/__init__.py
bazooka/api.py
bazooka/client.py
bazooka/common.py
bazooka/correlation.py
bazooka/curl_logging.py
bazooka/exceptions.py
bazooka/sessions.py
bazooka/tests/__init__.py
bazooka/tests/base.py
bazooka/tests/test_client.py
bazooka/tests/test_correlation.py
bazooka/tests/test_curl_logging.py
bazooka/tests/test_retryable_sessions.py
bazooka/tests/test_sessions.py
bazooka-1.3.1.dist-info/licenses/AUTHORS
bazooka-1.3.1.dist-info/licenses/LICENSE
bazooka-1.3.1.dist-info/METADATA
bazooka-1.3.1.dist-info/WHEEL
bazooka-1.3.1.dist-info/pbr.json
bazooka-1.3.1.dist-info/top_level.txt
bazooka-1.3.1.dist-info/RECORD
